mcp_server_hive/__init__.py
mcp_server_hive/server.py
mcp_server_hive-0.6.17.dist-info/METADATA
mcp_server_hive-0.6.17.dist-info/WHEEL
mcp_server_hive-0.6.17.dist-info/entry_points.txt
mcp_server_hive-0.6.17.dist-info/RECORD
