Metadata-Version: 2.4
Name: mcp-server-hive
Version: 0.6.17
Summary: A Hive MCP server for data analysis
Requires-Python: >=3.10
Requires-Dist: mcp>=1.0.0
Requires-Dist: pyhive
Requires-Dist: thrift-sasl>=0.4.3
Provides-Extra: dev
Requires-Dist: black>=23.0.0; extra == 'dev'
Requires-Dist: pyright>=1.1.389; extra == 'dev'
Requires-Dist: pytest-asyncio>=0.25.0; extra == 'dev'
Requires-Dist: pytest-cov>=4.0.0; extra == 'dev'
Requires-Dist: pytest>=7.0.0; extra == 'dev'
